LICENSE
MANIFEST.in
README.rst
setup.py
dj_sso_client.egg-info/PKG-INFO
dj_sso_client.egg-info/SOURCES.txt
dj_sso_client.egg-info/dependency_links.txt
dj_sso_client.egg-info/top_level.txt
djssoclient/__init__.py
djssoclient/admin.py
djssoclient/apiclient.py
djssoclient/authbackend.py
djssoclient/models.py
djssoclient/tests.py
djssoclient/urls.py
djssoclient/userstorage.py
djssoclient/version.py
djssoclient/views.py
djssoclient/migrations/0001_initial.py
djssoclient/migrations/__init__.py
example/.DS_Store
example/ssoclient/.DS_Store
example/ssoclient/db.sqlite3
example/ssoclient/manage.py
example/ssoclient/requirements.txt
example/ssoclient/.idea/.name
example/ssoclient/.idea/dataSources.ids
example/ssoclient/.idea/dataSources.local.xml
example/ssoclient/.idea/dataSources.xml
example/ssoclient/.idea/encodings.xml
example/ssoclient/.idea/misc.xml
example/ssoclient/.idea/modules.xml
example/ssoclient/.idea/ssoclient.iml
example/ssoclient/.idea/vcs.xml
example/ssoclient/.idea/workspace.xml
example/ssoclient/.idea/inspectionProfiles/Project_Default.xml
example/ssoclient/.idea/inspectionProfiles/profiles_settings.xml
example/ssoclient/.idea/scopes/scope_settings.xml
example/ssoclient/ssoclient/.DS_Store
example/ssoclient/ssoclient/__init__.py
example/ssoclient/ssoclient/__init__.pyc
example/ssoclient/ssoclient/settings.py
example/ssoclient/ssoclient/settings.pyc
example/ssoclient/ssoclient/urls.py
example/ssoclient/ssoclient/urls.pyc
example/ssoclient/ssoclient/views.py
example/ssoclient/ssoclient/views.pyc
example/ssoclient/ssoclient/wsgi.py
example/ssoclient/ssoclient/wsgi.pyc
example/ssoclient/templates/index.html