Metadata-Version: 1.1
Name: dj-sso-client
Version: 0.21
Summary: A Django SSO client application, works with dj-sso-server
Home-page: https://github.com/feifangit/dj-sso-client
Author: Fan Fei
Author-email: feifan.pub@gmail.com
License: GPL v2.0
Platform: UNKNOWN
Classifier: Environment :: Web Environment
Classifier: Framework :: Django
Classifier: Intended Audience :: Developers
Classifier: License :: OSI Approved :: GNU General Public License v2 (GPLv2)
Classifier: Operating System :: OS Independent
Classifier: Programming Language :: Python
Classifier: Programming Language :: Python :: 2
Classifier: Programming Language :: Python :: 2.6
Classifier: Programming Language :: Python :: 2.7
Classifier: Topic :: Internet :: WWW/HTTP
Classifier: Topic :: Internet :: WWW/HTTP :: Dynamic Content
